{"assets/AmI01_Einfuehrung.pdf":["assets/AmI01_Einfuehrung.pdf"],"assets/AmI02_Sensoren Aktoren.pdf":["assets/AmI02_Sensoren Aktoren.pdf"],"assets/AmI03_Mikrocontroller.pdf":["assets/AmI03_Mikrocontroller.pdf"],"assets/AmI04_Kommunikation.pdf":["assets/AmI04_Kommunikation.pdf"],"assets/AmI05_SmartHome.pdf":["assets/AmI05_SmartHome.pdf"],"assets/AmI06_Smart_City.pdf":["assets/AmI06_Smart_City.pdf"],"assets/AmI07_Gesundheitsversorgung.pdf":["assets/AmI07_Gesundheitsversorgung.pdf"],"assets/AmI08_Benutzerinteraktion.pdf":["assets/AmI08_Benutzerinteraktion.pdf"],"assets/AmI09_ContextAwareness.pdf":["assets/AmI09_ContextAwareness.pdf"],"assets/AmI10_KI.pdf":["assets/AmI10_KI.pdf"],"assets/AmI11_MaschinellesLernen.pdf":["assets/AmI11_MaschinellesLernen.pdf"],"assets/AmI12_Sicherheit.pdf":["assets/AmI12_Sicherheit.pdf"],"assets/AmI13_Datenschutz.pdf":["assets/AmI13_Datenschutz.pdf"],"assets/Vorlesungsskript_Ambient_Intelligence.pdf":["assets/Vorlesungsskript_Ambient_Intelligence.pdf"],"packages/cupertino_icons/assets/CupertinoIcons.ttf":["packages/cupertino_icons/assets/CupertinoIcons.ttf"]}